poexcel/__init__.py
poexcel/api/__init__.py
poexcel/api/excel.py
poexcel/core/ExcelType.py
poexcel/core/QueryExcel.py
poexcel/core/__init__.py
poexcel/lib/__init__.py
poexcel/lib/pandas_mem.py
poexcel/lib/excel/SplitExcel.py
poexcel/lib/excel/__init__.py
tests/__init__.py
tests/test_excel.py
poexcel-0.0.22.dist-info/LICENSE
poexcel-0.0.22.dist-info/METADATA
poexcel-0.0.22.dist-info/WHEEL
poexcel-0.0.22.dist-info/top_level.txt
poexcel-0.0.22.dist-info/RECORD
