Metadata-Version: 2.1
Name: poexcel
Version: 0.0.22
Summary: pip install poexcel
Home-page: https://www.python-office.com/
Author: CoderWanFeng
Author-email: 1957875073@qq.com
License: MIT
Project-URL: Bug Tracker, https://github.com/CoderWanFeng/poexcel/issues
Project-URL: Documentation, https://github.com/CoderWanFeng/poexcel/blob/master/README.md
Project-URL: Source Code, https://github.com/CoderWanFeng/poexcel
Platform: any
Requires-Python: >=3.7
License-File: LICENSE
Requires-Dist: pandas
Requires-Dist: faker
Requires-Dist: tqdm
Requires-Dist: xlrd
Requires-Dist: xlwt
Requires-Dist: poprogress
Requires-Dist: xlwings
Requires-Dist: pofile
Requires-Dist: requests
